{
  "id": "f3e2467f-9452-4ffd-b6b8-9f906e523c70",
  "name": "TEST_MM",
  "description": "",
  "metamodelRefs": [],
  "viewstyles": [
    {
      "id": "b4c9442c-d166-40ca-99fe-84f9581b9065",
      "name": "TEST_MM_Viewstyle",
      "description": "",
      "markedAsDeleted": false,
      "modified": false
    }
  ],
  "geometries": [],
  "objecttypes": [
    {
      "id": "5f1fa0f1-d89f-4a62-5b93-3a433acb833e",
      "name": "Container",
      "abstract": false,
      "viewkind": "Container",
      "typename": "Object type",
      "typedescription": "",
      "typeviewRef": "a3112875-e4fe-4100-b290-5634d8b8acfc",
      "description": "",
      "properties": [],
      "attributes": [],
      "methods": [],
      "leftPorts": [],
      "rightPorts": [],
      "topPorts": [],
      "bottomPorts": [],
      "markedAsDeleted": false,
      "modified": true
    },
    {
      "id": "c30f6e2c-d04b-4360-fc17-002d1c4162f8",
      "name": "Datatype",
      "abstract": false,
      "viewkind": "Object",
      "typename": "Object type",
      "typedescription": "",
      "typeviewRef": "1f906da8-da00-4068-06ed-6f670e17ef0f",
      "description": "",
      "properties": [],
      "attributes": [],
      "methods": [],
      "leftPorts": [],
      "rightPorts": [],
      "topPorts": [],
      "bottomPorts": [],
      "markedAsDeleted": false,
      "modified": true
    },
    {
      "id": "c0de4b48-0220-424a-dd07-e620e27bd3c8",
      "name": "Element",
      "abstract": true,
      "viewkind": "Object",
      "typename": "Object type",
      "typedescription": "",
      "typeviewRef": "6aad4796-8648-4c1b-b31e-7501afdcb19d",
      "description": "",
      "properties": [],
      "attributes": [],
      "methods": [],
      "leftPorts": [],
      "rightPorts": [],
      "topPorts": [],
      "bottomPorts": [],
      "markedAsDeleted": false,
      "modified": true
    },
    {
      "id": "31a18ce8-66cf-4b95-79e4-673746867ac3",
      "name": "EntityType",
      "abstract": false,
      "viewkind": "",
      "typename": "Object type",
      "typedescription": "",
      "typeviewRef": "2970b95c-f760-42c4-2c70-40723a79d921",
      "description": "",
      "properties": [],
      "attributes": [],
      "methods": [],
      "leftPorts": [],
      "rightPorts": [],
      "topPorts": [],
      "bottomPorts": [],
      "markedAsDeleted": false,
      "modified": true
    },
    {
      "id": "e07dbd76-f1ec-492e-cfce-c8cb5a2fab3c",
      "name": "FieldType",
      "abstract": false,
      "viewkind": "Object",
      "typename": "Object type",
      "typedescription": "",
      "typeviewRef": "a4ae2be6-3d6b-4b73-b6d0-a1f7ccd74738",
      "description": "",
      "properties": [
        {
          "id": "d210b11b-84eb-471d-aa93-15cb25b9f5db",
          "name": "fieldType",
          "defaultValue": "",
          "inputPattern": "",
          "viewFormat": "",
          "example": "",
          "markedAsDeleted": false,
          "modified": false,
          "description": "",
          "datatypeRef": "160e8cac-4003-4b00-175f-2b720ba088e0",
          "methodRef": "",
          "unitCategoryRef": ""
        }
      ],
      "attributes": [
        {
          "typeName": "FieldType",
          "propName": "fieldType",
          "name": "FieldType.fieldType",
          "propRef": "d210b11b-84eb-471d-aa93-15cb25b9f5db"
        }
      ],
      "methods": [],
      "leftPorts": [],
      "rightPorts": [],
      "topPorts": [],
      "bottomPorts": [],
      "markedAsDeleted": false,
      "modified": true
    },
    {
      "id": "5cc540c0-ea91-4401-74bb-4f7cb52a2366",
      "name": "Generic",
      "abstract": false,
      "viewkind": "Object",
      "typename": "Object type",
      "typedescription": "",
      "typeviewRef": "b42be04d-f9e5-4906-0459-80f43aada183",
      "description": "",
      "properties": [],
      "attributes": [],
      "methods": [],
      "leftPorts": [],
      "rightPorts": [],
      "topPorts": [],
      "bottomPorts": [],
      "markedAsDeleted": false,
      "modified": true
    },
    {
      "id": "b5cd30a2-6213-402a-a64a-85c6eff312f5",
      "name": "InputPattern",
      "abstract": false,
      "viewkind": "Object",
      "typename": "Object type",
      "typedescription": "",
      "typeviewRef": "6c825361-c99d-4441-3e00-325e78ea969c",
      "description": "",
      "properties": [
        {
          "id": "95292049-811b-46d0-c202-bba9466fde50",
          "name": "pattern",
          "defaultValue": "",
          "inputPattern": "",
          "viewFormat": "",
          "example": "",
          "markedAsDeleted": false,
          "modified": false,
          "description": "",
          "datatypeRef": "160e8cac-4003-4b00-175f-2b720ba088e0",
          "methodRef": "",
          "unitCategoryRef": ""
        }
      ],
      "attributes": [
        {
          "typeName": "InputPattern",
          "propName": "pattern",
          "name": "InputPattern.pattern",
          "propRef": "95292049-811b-46d0-c202-bba9466fde50"
        }
      ],
      "methods": [],
      "leftPorts": [],
      "rightPorts": [],
      "topPorts": [],
      "bottomPorts": [],
      "markedAsDeleted": false,
      "modified": true
    },
    {
      "id": "c7b60c43-cb91-4e92-a4b6-53d2aba052f3",
      "name": "Label",
      "abstract": false,
      "viewkind": "Object",
      "typename": "Object type",
      "typedescription": "",
      "typeviewRef": "4be6622d-82a6-4b8c-a872-df6e9fcc8d3a",
      "description": "",
      "properties": [
        {
          "id": "f2a07c3b-025f-483c-327a-7e6a8f6b283b",
          "name": "text",
          "defaultValue": "",
          "inputPattern": "",
          "viewFormat": "",
          "example": "",
          "markedAsDeleted": false,
          "modified": false,
          "description": "",
          "datatypeRef": "7c4672a0-c6ee-48a2-0bc5-e344d1564cbb",
          "methodRef": "",
          "unitCategoryRef": ""
        }
      ],
      "attributes": [
        {
          "typeName": "Label",
          "propName": "text",
          "name": "Label.text",
          "propRef": "f2a07c3b-025f-483c-327a-7e6a8f6b283b"
        }
      ],
      "methods": [],
      "leftPorts": [],
      "rightPorts": [],
      "topPorts": [],
      "bottomPorts": [],
      "markedAsDeleted": false,
      "modified": true
    },
    {
      "id": "4f1e3080-24b0-4e9f-f8cc-f13e469232a2",
      "name": "Method",
      "abstract": false,
      "viewkind": "Object",
      "typename": "Object type",
      "typedescription": "",
      "typeviewRef": "35bdb5f9-49c9-4ce0-471d-efc648d41fc1",
      "description": "",
      "properties": [
        {
          "id": "d836ad9a-00f6-4cf2-2986-9ca1b4e71498",
          "name": "methodtype",
          "defaultValue": "",
          "inputPattern": "",
          "viewFormat": "",
          "example": "",
          "markedAsDeleted": false,
          "modified": false,
          "description": "",
          "datatypeRef": "160e8cac-4003-4b00-175f-2b720ba088e0",
          "methodRef": "",
          "unitCategoryRef": ""
        }
      ],
      "attributes": [
        {
          "typeName": "Method",
          "propName": "methodtype",
          "name": "Method.methodtype",
          "propRef": "d836ad9a-00f6-4cf2-2986-9ca1b4e71498"
        }
      ],
      "methods": [],
      "leftPorts": [],
      "rightPorts": [],
      "topPorts": [],
      "bottomPorts": [],
      "markedAsDeleted": false,
      "modified": true
    },
    {
      "id": "e0708fcb-4dab-44fb-312d-7685ea332985",
      "name": "MethodType",
      "abstract": false,
      "viewkind": "Object",
      "typename": "Object type",
      "typedescription": "",
      "typeviewRef": "b5f05f73-b85b-4fb9-2cab-f67084239e8b",
      "description": "",
      "properties": [],
      "attributes": [],
      "methods": [],
      "leftPorts": [],
      "rightPorts": [],
      "topPorts": [],
      "bottomPorts": [],
      "markedAsDeleted": false,
      "modified": true
    },
    {
      "id": "7b543680-f667-4db7-2344-8af95e654941",
      "name": "Port",
      "abstract": false,
      "viewkind": "",
      "typename": "Object type",
      "typedescription": "",
      "typeviewRef": "e3d64119-7f68-48a9-e155-c00653569556",
      "description": "",
      "properties": [
        {
          "id": "5064958a-86d4-4290-8507-02f33f1d3743",
          "name": "side",
          "defaultValue": "",
          "inputPattern": "",
          "viewFormat": "",
          "example": "",
          "markedAsDeleted": false,
          "modified": false,
          "description": "",
          "datatypeRef": "ab00c936-a38b-4f04-d583-67f8963a3b2b",
          "methodRef": "",
          "unitCategoryRef": ""
        }
      ],
      "attributes": [
        {
          "typeName": "Port",
          "propName": "side",
          "name": "Port.side",
          "propRef": "5064958a-86d4-4290-8507-02f33f1d3743"
        }
      ],
      "methods": [],
      "leftPorts": [],
      "rightPorts": [],
      "topPorts": [],
      "bottomPorts": [],
      "markedAsDeleted": false,
      "modified": true
    },
    {
      "id": "7e9386c9-75bc-4239-c040-d328f1c91e1b",
      "name": "Property",
      "abstract": false,
      "viewkind": "Object",
      "typename": "Object type",
      "typedescription": "",
      "typeviewRef": "e05d9ee2-7592-4313-4b53-865f7964294a",
      "description": "",
      "properties": [],
      "attributes": [],
      "methods": [],
      "leftPorts": [],
      "rightPorts": [],
      "topPorts": [],
      "bottomPorts": [],
      "markedAsDeleted": false,
      "modified": true
    },
    {
      "id": "4beef970-06ed-4f54-6589-5804e358a8a6",
      "name": "RelshipType",
      "abstract": false,
      "viewkind": "Object",
      "typename": "Object type",
      "typedescription": "",
      "typeviewRef": "a870109d-3297-44ea-118b-6712e8026cf5",
      "description": "",
      "properties": [],
      "attributes": [],
      "methods": [],
      "leftPorts": [],
      "rightPorts": [],
      "topPorts": [],
      "bottomPorts": [],
      "markedAsDeleted": false,
      "modified": true
    },
    {
      "id": "91c27596-9910-49c3-9088-44da75085f14",
      "name": "Value",
      "abstract": false,
      "viewkind": "Object",
      "typename": "Object type",
      "typedescription": "",
      "typeviewRef": "0dd90a4c-048b-48fc-5bab-4b02e108fd6d",
      "description": "",
      "properties": [],
      "attributes": [],
      "methods": [],
      "leftPorts": [],
      "rightPorts": [],
      "topPorts": [],
      "bottomPorts": [],
      "markedAsDeleted": false,
      "modified": true
    },
    {
      "id": "1b6ba1b5-f716-4777-deab-cf91b0f53218",
      "name": "ViewFormat",
      "abstract": false,
      "viewkind": "Object",
      "typename": "Object type",
      "typedescription": "",
      "typeviewRef": "549919d8-afec-43b0-8e43-11b9864940cd",
      "description": "",
      "properties": [
        {
          "id": "ed7f1d92-88ed-46bc-7dc9-0e5c55f83bdb",
          "name": "viewFormat",
          "defaultValue": "",
          "inputPattern": "",
          "viewFormat": "",
          "example": "",
          "markedAsDeleted": false,
          "modified": false,
          "description": "",
          "datatypeRef": "160e8cac-4003-4b00-175f-2b720ba088e0",
          "methodRef": "",
          "unitCategoryRef": ""
        }
      ],
      "attributes": [
        {
          "typeName": "ViewFormat",
          "propName": "viewFormat",
          "name": "ViewFormat.viewFormat",
          "propRef": "ed7f1d92-88ed-46bc-7dc9-0e5c55f83bdb"
        }
      ],
      "methods": [],
      "leftPorts": [],
      "rightPorts": [],
      "topPorts": [],
      "bottomPorts": [],
      "markedAsDeleted": false,
      "modified": true
    }
  ],
  "relshiptypes": [
    {
      "id": "5718b4c7-3aa1-4ee3-0a9d-5e7cdcd18a24",
      "name": "Is",
      "relshipkind": "Generalization",
      "viewkind": "",
      "fromobjtypeRef": "31a18ce8-66cf-4b95-79e4-673746867ac3",
      "toobjtypeRef": "c0de4b48-0220-424a-dd07-e620e27bd3c8",
      "typeviewRef": "27eb5fd1-c46e-4edd-79fa-cf61f0ccc1f2",
      "description": "",
      "properties": [],
      "cardinality": "",
      "cardinalityFrom": "",
      "cardinalityTo": "",
      "nameFrom": "",
      "nameTo": "",
      "markedAsDeleted": false,
      "modified": false
    },
    {
      "id": "5c58ee46-38af-49e3-c2e0-cb58166cf9c7",
      "name": "Is",
      "relshipkind": "Generalization",
      "viewkind": "",
      "fromobjtypeRef": "5f1fa0f1-d89f-4a62-5b93-3a433acb833e",
      "toobjtypeRef": "c0de4b48-0220-424a-dd07-e620e27bd3c8",
      "typeviewRef": "69ed8cdc-61e9-45fa-a774-a1985b4dd76d",
      "description": "",
      "properties": [],
      "cardinality": "",
      "cardinalityFrom": "",
      "cardinalityTo": "",
      "nameFrom": "",
      "nameTo": "",
      "markedAsDeleted": false,
      "modified": false
    },
    {
      "id": "69a15677-c416-46c1-f1a6-ba51c6819d30",
      "name": "generic",
      "relshipkind": "Association",
      "viewkind": "",
      "fromobjtypeRef": "c0de4b48-0220-424a-dd07-e620e27bd3c8",
      "toobjtypeRef": "c0de4b48-0220-424a-dd07-e620e27bd3c8",
      "typeviewRef": "c4190b47-3a82-4032-f6e1-8cd7259e93b6",
      "description": "",
      "properties": [],
      "cardinality": "",
      "cardinalityFrom": "",
      "cardinalityTo": "",
      "nameFrom": "",
      "nameTo": "",
      "markedAsDeleted": false,
      "modified": false
    },
    {
      "id": "32f941fb-51df-431b-ffbb-5a3a75218862",
      "name": "Is",
      "relshipkind": "Generalization",
      "viewkind": "",
      "fromobjtypeRef": "5cc540c0-ea91-4401-74bb-4f7cb52a2366",
      "toobjtypeRef": "c0de4b48-0220-424a-dd07-e620e27bd3c8",
      "typeviewRef": "c2a8a6fe-14d7-42f3-8c45-08e2b3a2db07",
      "description": "",
      "properties": [],
      "cardinality": "",
      "cardinalityFrom": "",
      "cardinalityTo": "",
      "nameFrom": "",
      "nameTo": "",
      "markedAsDeleted": false,
      "modified": false
    },
    {
      "id": "c441a883-b9df-4f08-e447-20a1ff13cbab",
      "name": "hasContent",
      "relshipkind": "Association",
      "viewkind": "",
      "fromobjtypeRef": "31a18ce8-66cf-4b95-79e4-673746867ac3",
      "toobjtypeRef": "5f1fa0f1-d89f-4a62-5b93-3a433acb833e",
      "typeviewRef": "c6580e05-bf60-4420-bbe3-38d359c0a366",
      "description": "",
      "properties": [],
      "cardinality": "",
      "cardinalityFrom": "",
      "cardinalityTo": "",
      "nameFrom": "",
      "nameTo": "",
      "markedAsDeleted": false,
      "modified": false
    },
    {
      "id": "9c2f4dd9-297a-4221-c694-76a7c18ab04d",
      "name": "relationshipType",
      "relshipkind": "Association",
      "viewkind": "",
      "fromobjtypeRef": "31a18ce8-66cf-4b95-79e4-673746867ac3",
      "toobjtypeRef": "31a18ce8-66cf-4b95-79e4-673746867ac3",
      "typeviewRef": "70e7b709-bd91-4b7c-f390-553914e10430",
      "description": "",
      "properties": [],
      "cardinality": "",
      "cardinalityFrom": "",
      "cardinalityTo": "",
      "nameFrom": "",
      "nameTo": "",
      "markedAsDeleted": false,
      "modified": false
    },
    {
      "id": "a4fea123-cea6-4529-2c31-a38dab476e04",
      "name": "annotates",
      "relshipkind": "Association",
      "viewkind": "",
      "fromobjtypeRef": "c7b60c43-cb91-4e92-a4b6-53d2aba052f3",
      "toobjtypeRef": "c0de4b48-0220-424a-dd07-e620e27bd3c8",
      "typeviewRef": "8503a5ef-2f0f-49eb-1ac4-610871cb1508",
      "description": "",
      "properties": [],
      "cardinality": "",
      "cardinalityFrom": "",
      "cardinalityTo": "",
      "nameFrom": "",
      "nameTo": "",
      "markedAsDeleted": false,
      "modified": false
    },
    {
      "id": "22f50fa8-90be-4738-8f71-670a19668fe0",
      "name": "has",
      "relshipkind": "Association",
      "viewkind": "",
      "fromobjtypeRef": "31a18ce8-66cf-4b95-79e4-673746867ac3",
      "toobjtypeRef": "7e9386c9-75bc-4239-c040-d328f1c91e1b",
      "typeviewRef": "32adedbc-a6db-4bd9-ce39-977921b1cd50",
      "description": "",
      "properties": [],
      "cardinality": "",
      "cardinalityFrom": "",
      "cardinalityTo": "",
      "nameFrom": "",
      "nameTo": "",
      "markedAsDeleted": false,
      "modified": false
    },
    {
      "id": "1839b2e5-4b21-434d-8ee1-f88745d396da",
      "name": "Is",
      "relshipkind": "Generalization",
      "viewkind": "",
      "fromobjtypeRef": "7e9386c9-75bc-4239-c040-d328f1c91e1b",
      "toobjtypeRef": "31a18ce8-66cf-4b95-79e4-673746867ac3",
      "typeviewRef": "f43c5769-bd6a-455f-669f-d39e5d299935",
      "description": "",
      "properties": [],
      "cardinality": "",
      "cardinalityFrom": "",
      "cardinalityTo": "",
      "nameFrom": "",
      "nameTo": "",
      "markedAsDeleted": false,
      "modified": false
    },
    {
      "id": "c1716ead-9945-44d8-b7a8-f699ccaae48b",
      "name": "has",
      "relshipkind": "Association",
      "viewkind": "",
      "fromobjtypeRef": "7e9386c9-75bc-4239-c040-d328f1c91e1b",
      "toobjtypeRef": "91c27596-9910-49c3-9088-44da75085f14",
      "typeviewRef": "f9c14c3a-cf70-43c3-28cd-f8933e17e1a4",
      "description": "",
      "properties": [],
      "cardinality": "",
      "cardinalityFrom": "",
      "cardinalityTo": "",
      "nameFrom": "",
      "nameTo": "",
      "markedAsDeleted": false,
      "modified": false
    },
    {
      "id": "b1706580-fc46-41b2-2339-7fea9eba9634",
      "name": "isOf",
      "relshipkind": "Association",
      "viewkind": "",
      "fromobjtypeRef": "7e9386c9-75bc-4239-c040-d328f1c91e1b",
      "toobjtypeRef": "c30f6e2c-d04b-4360-fc17-002d1c4162f8",
      "typeviewRef": "54c8e777-6f6c-4250-3e0c-cfe6e406bcc3",
      "description": "",
      "properties": [],
      "cardinality": "",
      "cardinalityFrom": "",
      "cardinalityTo": "",
      "nameFrom": "",
      "nameTo": "",
      "markedAsDeleted": false,
      "modified": false
    },
    {
      "id": "443a5498-5f4b-4870-aae7-367445e4cd1b",
      "name": "has",
      "relshipkind": "Association",
      "viewkind": "",
      "fromobjtypeRef": "c30f6e2c-d04b-4360-fc17-002d1c4162f8",
      "toobjtypeRef": "e07dbd76-f1ec-492e-cfce-c8cb5a2fab3c",
      "typeviewRef": "892b29c0-6e9c-429b-d6f9-1c31d22d9031",
      "description": "",
      "properties": [],
      "cardinality": "",
      "cardinalityFrom": "",
      "cardinalityTo": "",
      "nameFrom": "",
      "nameTo": "",
      "markedAsDeleted": false,
      "modified": false
    },
    {
      "id": "89116b67-d68e-4d41-b69e-6f679e3a5ec2",
      "name": "has",
      "relshipkind": "Association",
      "viewkind": "",
      "fromobjtypeRef": "c30f6e2c-d04b-4360-fc17-002d1c4162f8",
      "toobjtypeRef": "1b6ba1b5-f716-4777-deab-cf91b0f53218",
      "typeviewRef": "e1b136c7-018d-4dd8-33bd-82e075b322b2",
      "description": "",
      "properties": [],
      "cardinality": "",
      "cardinalityFrom": "",
      "cardinalityTo": "",
      "nameFrom": "",
      "nameTo": "",
      "markedAsDeleted": false,
      "modified": false
    },
    {
      "id": "dd48d94f-bfd9-4785-14a4-540f9334a85e",
      "name": "has",
      "relshipkind": "Association",
      "viewkind": "",
      "fromobjtypeRef": "c30f6e2c-d04b-4360-fc17-002d1c4162f8",
      "toobjtypeRef": "b5cd30a2-6213-402a-a64a-85c6eff312f5",
      "typeviewRef": "b48b2cb8-0d9c-4bc8-baae-61c5d916b2d0",
      "description": "",
      "properties": [],
      "cardinality": "",
      "cardinalityFrom": "",
      "cardinalityTo": "",
      "nameFrom": "",
      "nameTo": "",
      "markedAsDeleted": false,
      "modified": false
    },
    {
      "id": "2898265c-33b9-4a5b-87b7-a913805f58bf",
      "name": "hasAllowed",
      "relshipkind": "Association",
      "viewkind": "",
      "fromobjtypeRef": "c30f6e2c-d04b-4360-fc17-002d1c4162f8",
      "toobjtypeRef": "91c27596-9910-49c3-9088-44da75085f14",
      "typeviewRef": "3e1ac72c-1a2e-40dd-b673-d78ca0777dd8",
      "description": "",
      "properties": [],
      "cardinality": "",
      "cardinalityFrom": "",
      "cardinalityTo": "",
      "nameFrom": "",
      "nameTo": "",
      "markedAsDeleted": false,
      "modified": false
    },
    {
      "id": "54e8e8e8-5138-45ec-9ef9-93b6b391235f",
      "name": "isDefault",
      "relshipkind": "Association",
      "viewkind": "",
      "fromobjtypeRef": "c30f6e2c-d04b-4360-fc17-002d1c4162f8",
      "toobjtypeRef": "91c27596-9910-49c3-9088-44da75085f14",
      "typeviewRef": "1ca7851f-f1d9-4965-ab51-72ba7ea3ec56",
      "description": "",
      "properties": [],
      "cardinality": "",
      "cardinalityFrom": "",
      "cardinalityTo": "",
      "nameFrom": "",
      "nameTo": "",
      "markedAsDeleted": false,
      "modified": false
    },
    {
      "id": "6e8fa497-32c2-4d0f-91b6-25c4b2dee58b",
      "name": "Is",
      "relshipkind": "Generalization",
      "viewkind": "",
      "fromobjtypeRef": "91c27596-9910-49c3-9088-44da75085f14",
      "toobjtypeRef": "c0de4b48-0220-424a-dd07-e620e27bd3c8",
      "typeviewRef": "874f7c58-c613-4da9-56b7-035d02e28dc3",
      "description": "",
      "properties": [],
      "cardinality": "",
      "cardinalityFrom": "",
      "cardinalityTo": "",
      "nameFrom": "",
      "nameTo": "",
      "markedAsDeleted": false,
      "modified": false
    },
    {
      "id": "0192a5a5-8e40-49d3-8bad-e4daeb785e81",
      "name": "Is",
      "relshipkind": "Generalization",
      "viewkind": "",
      "fromobjtypeRef": "c30f6e2c-d04b-4360-fc17-002d1c4162f8",
      "toobjtypeRef": "31a18ce8-66cf-4b95-79e4-673746867ac3",
      "typeviewRef": "e7c6f03b-d5a7-42c9-171e-e78e658c5fe2",
      "description": "",
      "properties": [],
      "cardinality": "",
      "cardinalityFrom": "",
      "cardinalityTo": "",
      "nameFrom": "",
      "nameTo": "",
      "markedAsDeleted": false,
      "modified": false
    },
    {
      "id": "8397f4a4-f8f5-4958-cf78-e99f506e0792",
      "name": "has",
      "relshipkind": "Association",
      "viewkind": "",
      "fromobjtypeRef": "31a18ce8-66cf-4b95-79e4-673746867ac3",
      "toobjtypeRef": "4f1e3080-24b0-4e9f-f8cc-f13e469232a2",
      "typeviewRef": "063bfe99-b439-4ffa-f1cd-a4438cb8c29e",
      "description": "",
      "properties": [],
      "cardinality": "",
      "cardinalityFrom": "",
      "cardinalityTo": "",
      "nameFrom": "",
      "nameTo": "",
      "markedAsDeleted": false,
      "modified": true
    },
    {
      "id": "6200a1f1-90e4-4e40-5215-56a277780666",
      "name": "Is",
      "relshipkind": "Generalization",
      "viewkind": "",
      "fromobjtypeRef": "4f1e3080-24b0-4e9f-f8cc-f13e469232a2",
      "toobjtypeRef": "31a18ce8-66cf-4b95-79e4-673746867ac3",
      "typeviewRef": "fbbc7e02-134c-4057-1286-0b829ed25c63",
      "description": "",
      "properties": [],
      "cardinality": "",
      "cardinalityFrom": "",
      "cardinalityTo": "",
      "nameFrom": "",
      "nameTo": "",
      "markedAsDeleted": false,
      "modified": false
    },
    {
      "id": "1ef01bf6-c3d6-4a6e-1354-d4d833199052",
      "name": "isOf",
      "relshipkind": "Association",
      "viewkind": "",
      "fromobjtypeRef": "c30f6e2c-d04b-4360-fc17-002d1c4162f8",
      "toobjtypeRef": "c30f6e2c-d04b-4360-fc17-002d1c4162f8",
      "typeviewRef": "399fbde1-1c9f-4c32-769d-fca04daf2159",
      "description": "",
      "properties": [],
      "cardinality": "",
      "cardinalityFrom": "",
      "cardinalityTo": "",
      "nameFrom": "",
      "nameTo": "",
      "markedAsDeleted": false,
      "modified": false
    },
    {
      "id": "f91bc898-4d25-4617-8ed6-bb9d071c468c",
      "name": "isOf",
      "relshipkind": "Association",
      "viewkind": "",
      "fromobjtypeRef": "4f1e3080-24b0-4e9f-f8cc-f13e469232a2",
      "toobjtypeRef": "e0708fcb-4dab-44fb-312d-7685ea332985",
      "typeviewRef": "be59cc7b-5c00-41d4-c48d-834202171b45",
      "description": "",
      "properties": [],
      "cardinality": "",
      "cardinalityFrom": "",
      "cardinalityTo": "",
      "nameFrom": "",
      "nameTo": "",
      "markedAsDeleted": false,
      "modified": false
    },
    {
      "id": "01529391-f452-40b0-9b0a-965171169881",
      "name": "Is",
      "relshipkind": "Generalization",
      "viewkind": "",
      "fromobjtypeRef": "e0708fcb-4dab-44fb-312d-7685ea332985",
      "toobjtypeRef": "31a18ce8-66cf-4b95-79e4-673746867ac3",
      "typeviewRef": "ec3d7b4b-f489-4343-6265-baf947077b22",
      "description": "",
      "properties": [],
      "cardinality": "",
      "cardinalityFrom": "",
      "cardinalityTo": "",
      "nameFrom": "",
      "nameTo": "",
      "markedAsDeleted": false,
      "modified": false
    },
    {
      "id": "2c019c92-ca60-47fb-c5c2-daaeed8e9c03",
      "name": "has",
      "relshipkind": "Association",
      "viewkind": "",
      "fromobjtypeRef": "e0708fcb-4dab-44fb-312d-7685ea332985",
      "toobjtypeRef": "7e9386c9-75bc-4239-c040-d328f1c91e1b",
      "typeviewRef": "e9911cf7-3271-4ef7-35f7-9fdafa8dfe67",
      "description": "",
      "properties": [],
      "cardinality": "",
      "cardinalityFrom": "",
      "cardinalityTo": "",
      "nameFrom": "",
      "nameTo": "",
      "markedAsDeleted": false,
      "modified": false
    },
    {
      "id": "a4fbd9fa-a018-487d-0d9f-3c7787a507f9",
      "name": "Is",
      "relshipkind": "Generalization",
      "viewkind": "",
      "fromobjtypeRef": "4beef970-06ed-4f54-6589-5804e358a8a6",
      "toobjtypeRef": "c0de4b48-0220-424a-dd07-e620e27bd3c8",
      "typeviewRef": "aef9ce27-8080-4408-0d54-1e1959d5b15f",
      "description": "",
      "properties": [],
      "cardinality": "",
      "cardinalityFrom": "",
      "cardinalityTo": "",
      "nameFrom": "",
      "nameTo": "",
      "markedAsDeleted": false,
      "modified": false
    },
    {
      "id": "ffba4fe9-bace-4bd3-0734-619f1c6e5c7a",
      "name": "from",
      "relshipkind": "Association",
      "viewkind": "",
      "fromobjtypeRef": "4beef970-06ed-4f54-6589-5804e358a8a6",
      "toobjtypeRef": "31a18ce8-66cf-4b95-79e4-673746867ac3",
      "typeviewRef": "da0c182a-72c2-4d2b-f052-410de1e80762",
      "description": "",
      "properties": [],
      "cardinality": "",
      "cardinalityFrom": "",
      "cardinalityTo": "",
      "nameFrom": "",
      "nameTo": "",
      "markedAsDeleted": false,
      "modified": false
    },
    {
      "id": "38be5614-3a23-4193-0aec-311c45f1f6a3",
      "name": "to",
      "relshipkind": "Association",
      "viewkind": "",
      "fromobjtypeRef": "4beef970-06ed-4f54-6589-5804e358a8a6",
      "toobjtypeRef": "31a18ce8-66cf-4b95-79e4-673746867ac3",
      "typeviewRef": "b8c49fd7-65af-42c6-c895-5f7ad9d247f4",
      "description": "",
      "properties": [],
      "cardinality": "",
      "cardinalityFrom": "",
      "cardinalityTo": "",
      "nameFrom": "",
      "nameTo": "",
      "markedAsDeleted": false,
      "modified": false
    },
    {
      "id": "1165d437-5ae7-4af4-8afb-37ae3430fd93",
      "name": "has",
      "relshipkind": "Association",
      "viewkind": "",
      "fromobjtypeRef": "4beef970-06ed-4f54-6589-5804e358a8a6",
      "toobjtypeRef": "7e9386c9-75bc-4239-c040-d328f1c91e1b",
      "typeviewRef": "f87bf8cc-f2e2-4fd6-a7d9-198e9af39dff",
      "description": "",
      "properties": [],
      "cardinality": "",
      "cardinalityFrom": "",
      "cardinalityTo": "",
      "nameFrom": "",
      "nameTo": "",
      "markedAsDeleted": false,
      "modified": false
    },
    {
      "id": "4e15d68d-8e3f-4de0-cf51-51ebfd363cb7",
      "name": "hasContent",
      "relshipkind": "Association",
      "viewkind": "",
      "fromobjtypeRef": "4beef970-06ed-4f54-6589-5804e358a8a6",
      "toobjtypeRef": "5f1fa0f1-d89f-4a62-5b93-3a433acb833e",
      "typeviewRef": "e0848d44-15b1-43fa-6b04-aadf4608666b",
      "description": "",
      "properties": [],
      "cardinality": "",
      "cardinalityFrom": "",
      "cardinalityTo": "",
      "nameFrom": "",
      "nameTo": "",
      "markedAsDeleted": false,
      "modified": false
    },
    {
      "id": "ebae050f-31cc-4b9a-c492-1ed65289a520",
      "name": "Is",
      "relshipkind": "Generalization",
      "viewkind": "",
      "fromobjtypeRef": "7b543680-f667-4db7-2344-8af95e654941",
      "toobjtypeRef": "31a18ce8-66cf-4b95-79e4-673746867ac3",
      "typeviewRef": "c52b2c07-671e-45dc-6488-672acaa9ac3c",
      "description": "",
      "properties": [],
      "cardinality": "",
      "cardinalityFrom": "",
      "cardinalityTo": "",
      "nameFrom": "",
      "nameTo": "",
      "markedAsDeleted": false,
      "modified": true
    },
    {
      "id": "94b66a28-b600-4430-311a-83444e55a05c",
      "name": "hasPort",
      "relshipkind": "Association",
      "viewkind": "",
      "fromobjtypeRef": "31a18ce8-66cf-4b95-79e4-673746867ac3",
      "toobjtypeRef": "7b543680-f667-4db7-2344-8af95e654941",
      "typeviewRef": "2188d263-8a0f-4d76-3d09-d6cfe555e027",
      "description": "",
      "properties": [],
      "cardinality": "",
      "cardinalityFrom": "",
      "cardinalityTo": "",
      "nameFrom": "",
      "nameTo": "",
      "markedAsDeleted": false,
      "modified": true
    }
  ],
  "objecttypes0": [
    {
      "id": "7b543680-f667-4db7-2344-8af95e654941",
      "name": "Port",
      "abstract": false,
      "viewkind": "",
      "typename": "Object type",
      "typedescription": "",
      "typeviewRef": "e3d64119-7f68-48a9-e155-c00653569556",
      "description": "",
      "properties": [
        {
          "id": "5064958a-86d4-4290-8507-02f33f1d3743",
          "name": "side",
          "defaultValue": "",
          "inputPattern": "",
          "viewFormat": "",
          "example": "",
          "markedAsDeleted": false,
          "modified": false,
          "description": "",
          "datatypeRef": "ab00c936-a38b-4f04-d583-67f8963a3b2b",
          "methodRef": "",
          "unitCategoryRef": ""
        }
      ],
      "attributes": [
        {
          "typeName": "Port",
          "propName": "side",
          "name": "Port.side",
          "propRef": "5064958a-86d4-4290-8507-02f33f1d3743"
        }
      ],
      "methods": [],
      "leftPorts": [],
      "rightPorts": [],
      "topPorts": [],
      "bottomPorts": [],
      "markedAsDeleted": false,
      "modified": true
    }
  ],
  "relshiptypes0": [
    {
      "id": "5718b4c7-3aa1-4ee3-0a9d-5e7cdcd18a24",
      "name": "Is",
      "relshipkind": "Generalization",
      "viewkind": "",
      "fromobjtypeRef": "31a18ce8-66cf-4b95-79e4-673746867ac3",
      "toobjtypeRef": "c0de4b48-0220-424a-dd07-e620e27bd3c8",
      "typeviewRef": "27eb5fd1-c46e-4edd-79fa-cf61f0ccc1f2",
      "description": "",
      "properties": [],
      "cardinality": "",
      "cardinalityFrom": "",
      "cardinalityTo": "",
      "nameFrom": "",
      "nameTo": "",
      "markedAsDeleted": false,
      "modified": false
    },
    {
      "id": "5c58ee46-38af-49e3-c2e0-cb58166cf9c7",
      "name": "Is",
      "relshipkind": "Generalization",
      "viewkind": "",
      "fromobjtypeRef": "5f1fa0f1-d89f-4a62-5b93-3a433acb833e",
      "toobjtypeRef": "c0de4b48-0220-424a-dd07-e620e27bd3c8",
      "typeviewRef": "69ed8cdc-61e9-45fa-a774-a1985b4dd76d",
      "description": "",
      "properties": [],
      "cardinality": "",
      "cardinalityFrom": "",
      "cardinalityTo": "",
      "nameFrom": "",
      "nameTo": "",
      "markedAsDeleted": false,
      "modified": false
    }
  ],
  "properties": [
    {
      "id": "f2a07c3b-025f-483c-327a-7e6a8f6b283b",
      "name": "text",
      "defaultValue": "",
      "inputPattern": "",
      "viewFormat": "",
      "example": "",
      "markedAsDeleted": false,
      "modified": false,
      "description": "",
      "datatypeRef": "7c4672a0-c6ee-48a2-0bc5-e344d1564cbb",
      "methodRef": "",
      "unitCategoryRef": ""
    },
    {
      "id": "d210b11b-84eb-471d-aa93-15cb25b9f5db",
      "name": "fieldType",
      "defaultValue": "",
      "inputPattern": "",
      "viewFormat": "",
      "example": "",
      "markedAsDeleted": false,
      "modified": false,
      "description": "",
      "datatypeRef": "160e8cac-4003-4b00-175f-2b720ba088e0",
      "methodRef": "",
      "unitCategoryRef": ""
    },
    {
      "id": "95292049-811b-46d0-c202-bba9466fde50",
      "name": "pattern",
      "defaultValue": "",
      "inputPattern": "",
      "viewFormat": "",
      "example": "",
      "markedAsDeleted": false,
      "modified": false,
      "description": "",
      "datatypeRef": "160e8cac-4003-4b00-175f-2b720ba088e0",
      "methodRef": "",
      "unitCategoryRef": ""
    },
    {
      "id": "d836ad9a-00f6-4cf2-2986-9ca1b4e71498",
      "name": "methodtype",
      "defaultValue": "",
      "inputPattern": "",
      "viewFormat": "",
      "example": "",
      "markedAsDeleted": false,
      "modified": false,
      "description": "",
      "datatypeRef": "160e8cac-4003-4b00-175f-2b720ba088e0",
      "methodRef": "",
      "unitCategoryRef": ""
    },
    {
      "id": "ed7f1d92-88ed-46bc-7dc9-0e5c55f83bdb",
      "name": "viewFormat",
      "defaultValue": "",
      "inputPattern": "",
      "viewFormat": "",
      "example": "",
      "markedAsDeleted": false,
      "modified": false,
      "description": "",
      "datatypeRef": "160e8cac-4003-4b00-175f-2b720ba088e0",
      "methodRef": "",
      "unitCategoryRef": ""
    },
    {
      "id": "5064958a-86d4-4290-8507-02f33f1d3743",
      "name": "side",
      "defaultValue": "",
      "inputPattern": "",
      "viewFormat": "",
      "example": "",
      "markedAsDeleted": false,
      "modified": false,
      "description": "",
      "datatypeRef": "ab00c936-a38b-4f04-d583-67f8963a3b2b",
      "methodRef": "",
      "unitCategoryRef": ""
    }
  ],
  "datatypes": [
    {
      "id": "ab00c936-a38b-4f04-d583-67f8963a3b2b",
      "name": "side",
      "description": "",
      "allowedValues": [
        "bottom",
        "top",
        "right",
        "left",
        " "
      ],
      "defaultValue": " ",
      "value": "",
      "inputPattern": "",
      "viewFormat": "",
      "fieldType": "radio",
      "markedAsDeleted": false,
      "modified": false
    },
    {
      "id": "abc274e1-f4e9-4d9c-7f98-b0ffe26499c9",
      "name": "cardinality",
      "description": "",
      "allowedValues": [
        "0-1",
        "1",
        "0-n",
        "1-n",
        "n"
      ],
      "defaultValue": "",
      "value": "",
      "inputPattern": "",
      "viewFormat": "%s",
      "fieldType": "select",
      "markedAsDeleted": false,
      "modified": false
    },
    {
      "id": "ae89dc9b-91ee-47a9-15a8-32ab3a593d03",
      "name": "viewkind",
      "description": "",
      "allowedValues": [
        "Object",
        "Container",
        "Subprocess"
      ],
      "defaultValue": "Object",
      "value": "",
      "inputPattern": "",
      "viewFormat": "%s",
      "fieldType": "radio",
      "markedAsDeleted": false,
      "modified": false
    },
    {
      "id": "2c460d8f-8b4f-402c-bd09-54177f28c330",
      "name": "relshipkind",
      "description": "",
      "allowedValues": [
        "Association",
        "Generalization",
        "Composition",
        "Aggregation"
      ],
      "defaultValue": "Association",
      "value": "",
      "inputPattern": "",
      "viewFormat": "%s",
      "fieldType": "radio",
      "markedAsDeleted": false,
      "modified": false
    },
    {
      "id": "c02679a8-aa20-4140-09c5-b5e6c2644185",
      "name": "layout",
      "description": "",
      "allowedValues": [
        "Circular",
        "Grid",
        "Tree",
        "ForceDirected",
        "LayeredDigraph",
        "Manual"
      ],
      "defaultValue": "Tree",
      "value": "",
      "inputPattern": "",
      "viewFormat": "%s",
      "fieldType": "radio",
      "markedAsDeleted": false,
      "modified": false
    },
    {
      "id": "38e214e8-80f4-4f4f-bf56-feff87579529",
      "name": "routing",
      "description": "",
      "allowedValues": [
        "AvoidsNodes",
        "Orthogonal",
        "Normal"
      ],
      "defaultValue": "Normal",
      "value": "",
      "inputPattern": "",
      "viewFormat": "%s",
      "fieldType": "radio",
      "markedAsDeleted": false,
      "modified": false
    },
    {
      "id": "8148679b-66b8-4035-27ff-d7e3435465f0",
      "name": "linkcurve",
      "description": "",
      "allowedValues": [
        "None",
        "Bezier",
        "JumpGap",
        "JumpOver"
      ],
      "defaultValue": "None",
      "value": "",
      "inputPattern": "",
      "viewFormat": "%s",
      "fieldType": "radio",
      "markedAsDeleted": false,
      "modified": false
    },
    {
      "id": "b044f60b-1763-480b-576f-4e4b110ba495",
      "name": "integer",
      "description": "Integer",
      "allowedValues": "",
      "defaultValue": null,
      "value": "",
      "inputPattern": "^[-+]?\\d+$",
      "viewFormat": "%d",
      "fieldType": "text",
      "markedAsDeleted": false,
      "modified": false
    },
    {
      "id": "160e8cac-4003-4b00-175f-2b720ba088e0",
      "name": "string",
      "description": "String",
      "allowedValues": "",
      "defaultValue": null,
      "value": "",
      "inputPattern": "",
      "viewFormat": "%s",
      "fieldType": "text",
      "markedAsDeleted": false,
      "modified": false
    },
    {
      "id": "5e614cf4-c91d-49a6-2e12-e033d7536682",
      "name": "number",
      "description": "Number",
      "allowedValues": "",
      "defaultValue": null,
      "value": "",
      "inputPattern": "^\\+?([1-9]\\d*)$",
      "viewFormat": "%f",
      "fieldType": "number",
      "markedAsDeleted": false,
      "modified": false
    },
    {
      "id": "9c426092-98be-4470-97d3-99ee033b6b29",
      "name": "boolean",
      "description": "Boolean",
      "allowedValues": "",
      "defaultValue": null,
      "value": "",
      "inputPattern": "[0-1]",
      "viewFormat": "",
      "fieldType": "checkbox",
      "markedAsDeleted": false,
      "modified": false
    },
    {
      "id": "b959f506-7609-4915-80dc-2b64270efa9f",
      "name": "date",
      "description": "Date",
      "allowedValues": "",
      "defaultValue": null,
      "value": "",
      "inputPattern": "",
      "viewFormat": "%s",
      "fieldType": "date",
      "markedAsDeleted": false,
      "modified": false
    },
    {
      "id": "4260f5d9-16ee-40e2-3503-1d4988f2c23a",
      "name": "reldir",
      "description": "",
      "allowedValues": [
        "in",
        "out"
      ],
      "defaultValue": "out",
      "value": "",
      "inputPattern": "",
      "viewFormat": "",
      "fieldType": "radio",
      "markedAsDeleted": false,
      "modified": false
    },
    {
      "id": "afc3d3bd-2a61-4e15-0503-c85bb300ca85",
      "name": "actiontype",
      "description": "",
      "allowedValues": [
        "Highlight",
        "Select"
      ],
      "defaultValue": "",
      "value": "",
      "inputPattern": "",
      "viewFormat": "",
      "fieldType": "radio",
      "markedAsDeleted": false,
      "modified": false
    },
    {
      "id": "3b483815-7737-466b-fc4e-237613a7ca5e",
      "name": "fieldType",
      "description": "",
      "allowedValues": [
        "checkbox",
        "color",
        "date",
        "email",
        "file",
        "image",
        "month",
        "number",
        "password",
        "radio",
        "range",
        "select",
        "text",
        "textarea",
        "time",
        "url",
        "week"
      ],
      "defaultValue": "text",
      "value": "",
      "inputPattern": "",
      "viewFormat": "%s",
      "fieldType": "radio",
      "markedAsDeleted": false,
      "modified": false
    },
    {
      "id": "7c4672a0-c6ee-48a2-0bc5-e344d1564cbb",
      "name": "textarea",
      "description": "",
      "allowedValues": null,
      "defaultValue": "",
      "value": "",
      "inputPattern": "",
      "viewFormat": "",
      "fieldType": "textarea",
      "markedAsDeleted": false,
      "modified": false
    },
    {
      "id": "ad81c088-0e5c-4c95-94dc-902d903c0b56",
      "name": "methodtype",
      "description": "",
      "allowedValues": [
        "propertyMethod",
        "aggregateValue",
        "objectMethod"
      ],
      "defaultValue": "",
      "value": "",
      "inputPattern": "",
      "viewFormat": "",
      "fieldType": "select",
      "markedAsDeleted": false,
      "modified": false
    }
  ],
  "methodtypes": [
    {
      "id": "3625c808-3d5c-498a-87cb-5a245a7a9dea",
      "name": "AggregateValue",
      "description": "",
      "properties": [
        {
          "id": "010fb767-99d2-4f25-0340-34150e459116",
          "name": "reltype",
          "nameId": "reltype",
          "category": "Property",
          "description": "",
          "markedAsDeleted": false,
          "modified": false,
          "fs_collection": "properties",
          "datatype": {
            "id": "160e8cac-4003-4b00-175f-2b720ba088e0",
            "name": "string",
            "nameId": "string",
            "category": "Datatype",
            "description": "String",
            "markedAsDeleted": false,
            "modified": false,
            "fs_collection": "datatypes",
            "isOfDatatype": null,
            "allowedValues": "",
            "defaultValue": null,
            "value": "",
            "inputPattern": "",
            "viewFormat": "%s",
            "fieldType": "text",
            "datatypeRef": ""
          },
          "datatypeRef": "",
          "method": null,
          "methodRef": "",
          "unitCategory": null,
          "unitCategoryRef": "",
          "defaultValue": "",
          "inputPattern": "",
          "viewFormat": "",
          "example": ""
        },
        {
          "id": "59240f6a-3a86-48eb-cc69-e070a0de7e65",
          "name": "reldir",
          "nameId": "reldir",
          "category": "Property",
          "description": "",
          "markedAsDeleted": false,
          "modified": false,
          "fs_collection": "properties",
          "datatype": {
            "id": "4260f5d9-16ee-40e2-3503-1d4988f2c23a",
            "name": "reldir",
            "nameId": "reldir",
            "category": "Datatype",
            "description": "",
            "markedAsDeleted": false,
            "modified": false,
            "fs_collection": "datatypes",
            "isOfDatatype": null,
            "allowedValues": [
              "in",
              "out"
            ],
            "defaultValue": "out",
            "value": "",
            "inputPattern": "",
            "viewFormat": "",
            "fieldType": "radio",
            "datatypeRef": ""
          },
          "datatypeRef": "",
          "method": null,
          "methodRef": "",
          "unitCategory": null,
          "unitCategoryRef": "",
          "defaultValue": "",
          "inputPattern": "",
          "viewFormat": "",
          "example": ""
        },
        {
          "id": "ca9c27a5-33b2-4fdf-c969-5716a06fe960",
          "name": "objtype",
          "nameId": "objtype",
          "category": "Property",
          "description": "",
          "markedAsDeleted": false,
          "modified": false,
          "fs_collection": "properties",
          "datatype": {
            "id": "160e8cac-4003-4b00-175f-2b720ba088e0",
            "name": "string",
            "nameId": "string",
            "category": "Datatype",
            "description": "String",
            "markedAsDeleted": false,
            "modified": false,
            "fs_collection": "datatypes",
            "isOfDatatype": null,
            "allowedValues": "",
            "defaultValue": null,
            "value": "",
            "inputPattern": "",
            "viewFormat": "%s",
            "fieldType": "text",
            "datatypeRef": ""
          },
          "datatypeRef": "",
          "method": null,
          "methodRef": "",
          "unitCategory": null,
          "unitCategoryRef": "",
          "defaultValue": "",
          "inputPattern": "",
          "viewFormat": "",
          "example": ""
        },
        {
          "id": "e658c82d-0282-4d86-3c78-3cc0ed912459",
          "name": "expression",
          "nameId": "expression",
          "category": "Property",
          "description": "",
          "markedAsDeleted": false,
          "modified": false,
          "fs_collection": "properties",
          "datatype": {
            "id": "160e8cac-4003-4b00-175f-2b720ba088e0",
            "name": "string",
            "nameId": "string",
            "category": "Datatype",
            "description": "String",
            "markedAsDeleted": false,
            "modified": false,
            "fs_collection": "datatypes",
            "isOfDatatype": null,
            "allowedValues": "",
            "defaultValue": null,
            "value": "",
            "inputPattern": "",
            "viewFormat": "%s",
            "fieldType": "text",
            "datatypeRef": ""
          },
          "datatypeRef": "",
          "method": null,
          "methodRef": "",
          "unitCategory": null,
          "unitCategoryRef": "",
          "defaultValue": "",
          "inputPattern": "",
          "viewFormat": "",
          "example": ""
        }
      ],
      "markedAsDeleted": false,
      "modified": false
    },
    {
      "id": "28381d9b-cfe6-4a49-70de-a92ffd2080e0",
      "name": "CalculateValue",
      "description": "",
      "properties": [
        {
          "id": "02c171f7-176a-46ef-81a5-83e1e62fb219",
          "name": "expression",
          "nameId": "expression",
          "category": "Property",
          "description": "",
          "markedAsDeleted": false,
          "modified": false,
          "fs_collection": "properties",
          "datatype": {
            "id": "160e8cac-4003-4b00-175f-2b720ba088e0",
            "name": "string",
            "nameId": "string",
            "category": "Datatype",
            "description": "String",
            "markedAsDeleted": false,
            "modified": false,
            "fs_collection": "datatypes",
            "isOfDatatype": null,
            "allowedValues": "",
            "defaultValue": null,
            "value": "",
            "inputPattern": "",
            "viewFormat": "%s",
            "fieldType": "text",
            "datatypeRef": ""
          },
          "datatypeRef": "",
          "method": null,
          "methodRef": "",
          "unitCategory": null,
          "unitCategoryRef": "",
          "defaultValue": "",
          "inputPattern": "",
          "viewFormat": "",
          "example": ""
        }
      ],
      "markedAsDeleted": false,
      "modified": false
    },
    {
      "id": "082a6b39-f7b3-42ab-d204-2b4361f0de4a",
      "name": "Traverse",
      "description": "",
      "properties": [
        {
          "id": "994673b9-afe3-4274-42fc-4df1e1d607ee",
          "name": "reltype",
          "nameId": "reltype",
          "category": "Property",
          "description": "",
          "markedAsDeleted": false,
          "modified": false,
          "fs_collection": "properties",
          "datatype": {
            "id": "160e8cac-4003-4b00-175f-2b720ba088e0",
            "name": "string",
            "nameId": "string",
            "category": "Datatype",
            "description": "String",
            "markedAsDeleted": false,
            "modified": false,
            "fs_collection": "datatypes",
            "isOfDatatype": null,
            "allowedValues": "",
            "defaultValue": null,
            "value": "",
            "inputPattern": "",
            "viewFormat": "%s",
            "fieldType": "text",
            "datatypeRef": ""
          },
          "datatypeRef": "",
          "method": null,
          "methodRef": "",
          "unitCategory": null,
          "unitCategoryRef": "",
          "defaultValue": "",
          "inputPattern": "",
          "viewFormat": "",
          "example": ""
        },
        {
          "id": "178b9cb0-a012-41e9-3a77-664966915b07",
          "name": "reldir",
          "nameId": "reldir",
          "category": "Property",
          "description": "",
          "markedAsDeleted": false,
          "modified": false,
          "fs_collection": "properties",
          "datatype": {
            "id": "4260f5d9-16ee-40e2-3503-1d4988f2c23a",
            "name": "reldir",
            "nameId": "reldir",
            "category": "Datatype",
            "description": "",
            "markedAsDeleted": false,
            "modified": false,
            "fs_collection": "datatypes",
            "isOfDatatype": null,
            "allowedValues": [
              "in",
              "out"
            ],
            "defaultValue": "out",
            "value": "",
            "inputPattern": "",
            "viewFormat": "",
            "fieldType": "radio",
            "datatypeRef": ""
          },
          "datatypeRef": "",
          "method": null,
          "methodRef": "",
          "unitCategory": null,
          "unitCategoryRef": "",
          "defaultValue": "",
          "inputPattern": "",
          "viewFormat": "",
          "example": ""
        },
        {
          "id": "3098e39c-bb33-4c05-e91b-ab83465e1a5d",
          "name": "typecondition",
          "nameId": "typecondition",
          "category": "Property",
          "description": "",
          "markedAsDeleted": false,
          "modified": false,
          "fs_collection": "properties",
          "datatype": {
            "id": "160e8cac-4003-4b00-175f-2b720ba088e0",
            "name": "string",
            "nameId": "string",
            "category": "Datatype",
            "description": "String",
            "markedAsDeleted": false,
            "modified": false,
            "fs_collection": "datatypes",
            "isOfDatatype": null,
            "allowedValues": "",
            "defaultValue": null,
            "value": "",
            "inputPattern": "",
            "viewFormat": "%s",
            "fieldType": "text",
            "datatypeRef": ""
          },
          "datatypeRef": "",
          "method": null,
          "methodRef": "",
          "unitCategory": null,
          "unitCategoryRef": "",
          "defaultValue": "",
          "inputPattern": "",
          "viewFormat": "",
          "example": ""
        },
        {
          "id": "a52ed52b-540b-4d7f-f6fa-20d8c34f7f2c",
          "name": "valuecondition",
          "nameId": "valuecondition",
          "category": "Property",
          "description": "",
          "markedAsDeleted": false,
          "modified": false,
          "fs_collection": "properties",
          "datatype": {
            "id": "160e8cac-4003-4b00-175f-2b720ba088e0",
            "name": "string",
            "nameId": "string",
            "category": "Datatype",
            "description": "String",
            "markedAsDeleted": false,
            "modified": false,
            "fs_collection": "datatypes",
            "isOfDatatype": null,
            "allowedValues": "",
            "defaultValue": null,
            "value": "",
            "inputPattern": "",
            "viewFormat": "%s",
            "fieldType": "text",
            "datatypeRef": ""
          },
          "datatypeRef": "",
          "method": null,
          "methodRef": "",
          "unitCategory": null,
          "unitCategoryRef": "",
          "defaultValue": "",
          "inputPattern": "",
          "viewFormat": "",
          "example": ""
        },
        {
          "id": "7e488b8d-e935-4d6e-fa95-452104984a0b",
          "name": "preaction",
          "nameId": "preaction",
          "category": "Property",
          "description": "",
          "markedAsDeleted": false,
          "modified": false,
          "fs_collection": "properties",
          "datatype": {
            "id": "afc3d3bd-2a61-4e15-0503-c85bb300ca85",
            "name": "actiontype",
            "nameId": "actiontype",
            "category": "Datatype",
            "description": "",
            "markedAsDeleted": false,
            "modified": false,
            "fs_collection": "datatypes",
            "isOfDatatype": null,
            "allowedValues": [
              "Highlight",
              "Select"
            ],
            "defaultValue": "",
            "value": "",
            "inputPattern": "",
            "viewFormat": "",
            "fieldType": "radio",
            "datatypeRef": ""
          },
          "datatypeRef": "",
          "method": null,
          "methodRef": "",
          "unitCategory": null,
          "unitCategoryRef": "",
          "defaultValue": "",
          "inputPattern": "",
          "viewFormat": "",
          "example": ""
        },
        {
          "id": "3fc1cd64-c52e-479f-10a8-83b38f9c9242",
          "name": "postaction",
          "nameId": "postaction",
          "category": "Property",
          "description": "",
          "markedAsDeleted": false,
          "modified": false,
          "fs_collection": "properties",
          "datatype": {
            "id": "afc3d3bd-2a61-4e15-0503-c85bb300ca85",
            "name": "actiontype",
            "nameId": "actiontype",
            "category": "Datatype",
            "description": "",
            "markedAsDeleted": false,
            "modified": false,
            "fs_collection": "datatypes",
            "isOfDatatype": null,
            "allowedValues": [
              "Highlight",
              "Select"
            ],
            "defaultValue": "",
            "value": "",
            "inputPattern": "",
            "viewFormat": "",
            "fieldType": "radio",
            "datatypeRef": ""
          },
          "datatypeRef": "",
          "method": null,
          "methodRef": "",
          "unitCategory": null,
          "unitCategoryRef": "",
          "defaultValue": "",
          "inputPattern": "",
          "viewFormat": "",
          "example": ""
        }
      ],
      "markedAsDeleted": false,
      "modified": false
    }
  ],
  "methods": [],
  "units": [],
  "objecttypeviews": [
    {
      "id": "a3112875-e4fe-4100-b290-5634d8b8acfc",
      "name": "Container",
      "description": "",
      "typeRef": "5f1fa0f1-d89f-4a62-5b93-3a433acb833e",
      "viewkind": "Container",
      "template": "Container1",
      "figure": "",
      "geometry": "",
      "fillcolor": "white",
      "strokecolor": "black",
      "strokecolor1": "black",
      "strokecolor2": "black",
      "strokewidth": "1",
      "textcolor": "black",
      "textscale": "1",
      "memberscale": "1",
      "icon": "",
      "markedAsDeleted": false,
      "modified": false
    },
    {
      "id": "6aad4796-8648-4c1b-b31e-7501afdcb19d",
      "name": "Element",
      "description": "",
      "typeRef": "c0de4b48-0220-424a-dd07-e620e27bd3c8",
      "viewkind": "Object",
      "template": "textAndIcon",
      "figure": "",
      "geometry": "",
      "fillcolor": "lightgray",
      "strokecolor": "black",
      "strokecolor1": "black",
      "strokecolor2": "black",
      "strokewidth": "1",
      "textcolor": "black",
      "textscale": "1",
      "memberscale": "1",
      "icon": "",
      "markedAsDeleted": false,
      "modified": false
    },
    {
      "id": "2970b95c-f760-42c4-2c70-40723a79d921",
      "name": "EntityType",
      "description": "",
      "typeRef": "31a18ce8-66cf-4b95-79e4-673746867ac3",
      "viewkind": "Object",
      "template": "textAndIcon",
      "figure": "",
      "geometry": "",
      "fillcolor": "white",
      "strokecolor": "black",
      "strokecolor1": "black",
      "strokecolor2": "black",
      "strokewidth": "1",
      "textcolor": "black",
      "textscale": "1",
      "memberscale": 1,
      "icon": "",
      "markedAsDeleted": false,
      "modified": false
    },
    {
      "id": "b42be04d-f9e5-4906-0459-80f43aada183",
      "name": "Generic",
      "description": "",
      "typeRef": "5cc540c0-ea91-4401-74bb-4f7cb52a2366",
      "viewkind": "Object",
      "template": "textAndIcon",
      "figure": "",
      "geometry": "",
      "fillcolor": "#96c5b9",
      "strokecolor": "black",
      "strokecolor1": "black",
      "strokecolor2": "black",
      "strokewidth": "1",
      "textcolor": "black",
      "textscale": "1",
      "memberscale": "1",
      "icon": "./../images/default.png",
      "markedAsDeleted": false,
      "modified": false
    },
    {
      "id": "4be6622d-82a6-4b8c-a872-df6e9fcc8d3a",
      "name": "Label",
      "description": "",
      "typeRef": "c7b60c43-cb91-4e92-a4b6-53d2aba052f3",
      "viewkind": "Object",
      "template": "Annotation",
      "figure": "",
      "geometry": "",
      "fillcolor": "lightgrey",
      "strokecolor": "black",
      "strokecolor1": "black",
      "strokecolor2": "black",
      "strokewidth": "1",
      "textcolor": "black",
      "textscale": "1",
      "memberscale": "1",
      "icon": "",
      "markedAsDeleted": false,
      "modified": false
    },
    {
      "id": "1f906da8-da00-4068-06ed-6f670e17ef0f",
      "name": "Datatype",
      "description": "",
      "typeRef": "c30f6e2c-d04b-4360-fc17-002d1c4162f8",
      "viewkind": "Object",
      "template": "textAndIcon",
      "figure": "",
      "geometry": "",
      "fillcolor": "#d1ffee",
      "strokecolor": "black",
      "strokecolor1": "black",
      "strokecolor2": "black",
      "strokewidth": "1",
      "textcolor": "black",
      "textscale": "1",
      "memberscale": "1",
      "icon": "https://img.icons8.com/color/2x/data-.png",
      "markedAsDeleted": false,
      "modified": false
    },
    {
      "id": "a4ae2be6-3d6b-4b73-b6d0-a1f7ccd74738",
      "name": "FieldType",
      "description": "",
      "typeRef": "e07dbd76-f1ec-492e-cfce-c8cb5a2fab3c",
      "viewkind": "Object",
      "template": "textAndIcon",
      "figure": "",
      "geometry": "",
      "fillcolor": "#d1ffee",
      "strokecolor": "black",
      "strokecolor1": "black",
      "strokecolor2": "black",
      "strokewidth": "1",
      "textcolor": "black",
      "textscale": "1",
      "memberscale": "1",
      "icon": "",
      "markedAsDeleted": false,
      "modified": false
    },
    {
      "id": "6c825361-c99d-4441-3e00-325e78ea969c",
      "name": "InputPattern",
      "description": "",
      "typeRef": "b5cd30a2-6213-402a-a64a-85c6eff312f5",
      "viewkind": "Object",
      "template": "textAndIcon",
      "figure": "",
      "geometry": "",
      "fillcolor": "#d1ffee",
      "strokecolor": "black",
      "strokecolor1": "black",
      "strokecolor2": "black",
      "strokewidth": "1",
      "textcolor": "black",
      "textscale": "1",
      "memberscale": "1",
      "icon": "",
      "markedAsDeleted": false,
      "modified": false
    },
    {
      "id": "35bdb5f9-49c9-4ce0-471d-efc648d41fc1",
      "name": "Method",
      "description": "",
      "typeRef": "4f1e3080-24b0-4e9f-f8cc-f13e469232a2",
      "viewkind": "Object",
      "template": "textAndIcon",
      "figure": "",
      "geometry": "",
      "fillcolor": "#ead6f0",
      "strokecolor": "black",
      "strokecolor1": "black",
      "strokecolor2": "black",
      "strokewidth": "1",
      "textcolor": "black",
      "textscale": "1",
      "memberscale": "1",
      "icon": "",
      "markedAsDeleted": false,
      "modified": false
    },
    {
      "id": "b5f05f73-b85b-4fb9-2cab-f67084239e8b",
      "name": "MethodType",
      "description": "",
      "typeRef": "e0708fcb-4dab-44fb-312d-7685ea332985",
      "viewkind": "Object",
      "template": "textAndIcon",
      "figure": "",
      "geometry": "",
      "fillcolor": "#d6e6e1",
      "strokecolor": "black",
      "strokecolor1": "black",
      "strokecolor2": "black",
      "strokewidth": "1",
      "textcolor": "black",
      "textscale": "1",
      "memberscale": "1",
      "icon": "",
      "markedAsDeleted": false,
      "modified": false
    },
    {
      "id": "e05d9ee2-7592-4313-4b53-865f7964294a",
      "name": "Property",
      "description": "",
      "typeRef": "7e9386c9-75bc-4239-c040-d328f1c91e1b",
      "viewkind": "Object",
      "template": "textAndIcon",
      "figure": "",
      "geometry": "",
      "fillcolor": "lightgreen",
      "strokecolor": "black",
      "strokecolor1": "black",
      "strokecolor2": "black",
      "strokewidth": "1",
      "textcolor": "black",
      "textscale": "1",
      "memberscale": "1",
      "icon": "https://img.icons8.com/color/2x/add-property-1.png",
      "markedAsDeleted": false,
      "modified": false
    },
    {
      "id": "a870109d-3297-44ea-118b-6712e8026cf5",
      "name": "New Type",
      "description": "",
      "typeRef": "4beef970-06ed-4f54-6589-5804e358a8a6",
      "viewkind": "Object",
      "template": "textAndIcon",
      "figure": "",
      "geometry": "",
      "fillcolor": "#f4e6e8",
      "strokecolor": "black",
      "strokecolor1": "black",
      "strokecolor2": "black",
      "strokewidth": "1",
      "textcolor": "black",
      "textscale": "1",
      "memberscale": "1",
      "icon": "",
      "markedAsDeleted": false,
      "modified": false
    },
    {
      "id": "0dd90a4c-048b-48fc-5bab-4b02e108fd6d",
      "name": "Value",
      "description": "",
      "typeRef": "91c27596-9910-49c3-9088-44da75085f14",
      "viewkind": "Object",
      "template": "textAndIcon",
      "figure": "",
      "geometry": "",
      "fillcolor": "#d1ffee",
      "strokecolor": "black",
      "strokecolor1": "black",
      "strokecolor2": "black",
      "strokewidth": "1",
      "textcolor": "black",
      "textscale": "1",
      "memberscale": "1",
      "icon": "https://img.icons8.com/color/2x/variable.png",
      "markedAsDeleted": false,
      "modified": false
    },
    {
      "id": "549919d8-afec-43b0-8e43-11b9864940cd",
      "name": "ViewFormat",
      "description": "",
      "typeRef": "1b6ba1b5-f716-4777-deab-cf91b0f53218",
      "viewkind": "Object",
      "template": "textAndIcon",
      "figure": "",
      "geometry": "",
      "fillcolor": "#d1ffee",
      "strokecolor": "black",
      "strokecolor1": "black",
      "strokecolor2": "black",
      "strokewidth": "1",
      "textcolor": "black",
      "textscale": "1",
      "memberscale": "1",
      "icon": "",
      "markedAsDeleted": false,
      "modified": false
    },
    {
      "id": "e3d64119-7f68-48a9-e155-c00653569556",
      "name": "Port",
      "description": "",
      "typeRef": "7b543680-f667-4db7-2344-8af95e654941",
      "viewkind": "Object",
      "template": "textOnly",
      "figure": "",
      "geometry": "",
      "fillcolor": "white",
      "strokecolor": "black",
      "strokecolor1": "black",
      "strokecolor2": "black",
      "strokewidth": "1",
      "textcolor": "black",
      "textscale": "1",
      "memberscale": 1,
      "icon": "",
      "markedAsDeleted": false,
      "modified": false
    }
  ],
  "objtypegeos": [
    {
      "id": "e58974c8-82bd-4902-5300-fb39da88711f",
      "name": "",
      "typeRef": "5f1fa0f1-d89f-4a62-5b93-3a433acb833e",
      "metamodelRef": "f3e2467f-9452-4ffd-b6b8-9f906e523c70",
      "loc": "200 270",
      "size": "",
      "description": "",
      "markedAsDeleted": false,
      "modified": true
    },
    {
      "id": "ea4d8fc2-9c9c-4150-3056-9434e3af6af6",
      "name": "",
      "typeRef": "c0de4b48-0220-424a-dd07-e620e27bd3c8",
      "metamodelRef": "f3e2467f-9452-4ffd-b6b8-9f906e523c70",
      "loc": "-320 210",
      "size": "",
      "description": "",
      "markedAsDeleted": false,
      "modified": true
    },
    {
      "id": "5f58ac12-edf9-4368-444a-8428cbb0325e",
      "name": "",
      "typeRef": "31a18ce8-66cf-4b95-79e4-673746867ac3",
      "metamodelRef": "f3e2467f-9452-4ffd-b6b8-9f906e523c70",
      "loc": "220 60",
      "size": "",
      "description": "",
      "markedAsDeleted": false,
      "modified": false
    },
    {
      "id": "b7a1484f-da3e-4470-a9cd-46b0fea6b1eb",
      "name": "",
      "typeRef": "5cc540c0-ea91-4401-74bb-4f7cb52a2366",
      "metamodelRef": "f3e2467f-9452-4ffd-b6b8-9f906e523c70",
      "loc": "-180 350",
      "size": "",
      "description": "",
      "markedAsDeleted": false,
      "modified": true
    },
    {
      "id": "d0429880-e3d3-4258-a5ec-0b607e7b09d7",
      "name": "",
      "typeRef": "c7b60c43-cb91-4e92-a4b6-53d2aba052f3",
      "metamodelRef": "f3e2467f-9452-4ffd-b6b8-9f906e523c70",
      "loc": "-430 180",
      "size": "",
      "description": "",
      "markedAsDeleted": false,
      "modified": true
    },
    {
      "id": "ae2fde3f-d9f6-4b60-50cd-64b4bc38c781",
      "name": "",
      "typeRef": "5f1fa0f1-d89f-4a62-5b93-3a433acb833e",
      "metamodelRef": "f3e2467f-9452-4ffd-b6b8-9f906e523c70",
      "loc": "",
      "size": "",
      "description": "",
      "markedAsDeleted": false,
      "modified": false
    },
    {
      "id": "0e643ec1-42c6-4f4c-98b7-a6b6228c9af1",
      "name": "",
      "typeRef": "c30f6e2c-d04b-4360-fc17-002d1c4162f8",
      "metamodelRef": "f3e2467f-9452-4ffd-b6b8-9f906e523c70",
      "loc": "-490 -130",
      "size": "",
      "description": "",
      "markedAsDeleted": false,
      "modified": true
    },
    {
      "id": "83fa463b-62aa-4ce0-5032-381ebbdd3228",
      "name": "",
      "typeRef": "c0de4b48-0220-424a-dd07-e620e27bd3c8",
      "metamodelRef": "f3e2467f-9452-4ffd-b6b8-9f906e523c70",
      "loc": "",
      "size": "",
      "description": "",
      "markedAsDeleted": false,
      "modified": false
    },
    {
      "id": "59377f24-4925-4ae0-a715-fe1453d6b113",
      "name": "",
      "typeRef": "31a18ce8-66cf-4b95-79e4-673746867ac3",
      "metamodelRef": "f3e2467f-9452-4ffd-b6b8-9f906e523c70",
      "loc": "",
      "size": "",
      "description": "",
      "markedAsDeleted": false,
      "modified": false
    },
    {
      "id": "f8f45d13-c502-4813-d30b-7eff80143862",
      "name": "",
      "typeRef": "e07dbd76-f1ec-492e-cfce-c8cb5a2fab3c",
      "metamodelRef": "f3e2467f-9452-4ffd-b6b8-9f906e523c70",
      "loc": "-50 -280",
      "size": "",
      "description": "",
      "markedAsDeleted": false,
      "modified": true
    },
    {
      "id": "2abb1e7e-40ef-4419-926d-ea427cdb489c",
      "name": "",
      "typeRef": "5cc540c0-ea91-4401-74bb-4f7cb52a2366",
      "metamodelRef": "f3e2467f-9452-4ffd-b6b8-9f906e523c70",
      "loc": "",
      "size": "",
      "description": "",
      "markedAsDeleted": false,
      "modified": false
    },
    {
      "id": "d33cab36-ec20-464e-c34e-5b99857b036b",
      "name": "",
      "typeRef": "b5cd30a2-6213-402a-a64a-85c6eff312f5",
      "metamodelRef": "f3e2467f-9452-4ffd-b6b8-9f906e523c70",
      "loc": "-680 -320",
      "size": "",
      "description": "",
      "markedAsDeleted": false,
      "modified": true
    },
    {
      "id": "27b356d5-5efd-437a-b570-f36b97b7f2cb",
      "name": "",
      "typeRef": "c7b60c43-cb91-4e92-a4b6-53d2aba052f3",
      "metamodelRef": "f3e2467f-9452-4ffd-b6b8-9f906e523c70",
      "loc": "",
      "size": "",
      "description": "",
      "markedAsDeleted": false,
      "modified": false
    },
    {
      "id": "ffe777bd-9b2b-470b-23c7-cb04d3959c3a",
      "name": "",
      "typeRef": "4f1e3080-24b0-4e9f-f8cc-f13e469232a2",
      "metamodelRef": "f3e2467f-9452-4ffd-b6b8-9f906e523c70",
      "loc": "570 10",
      "size": "",
      "description": "",
      "markedAsDeleted": false,
      "modified": true
    },
    {
      "id": "a01c6ada-44eb-449b-ffd5-89c167dfa108",
      "name": "",
      "typeRef": "e0708fcb-4dab-44fb-312d-7685ea332985",
      "metamodelRef": "f3e2467f-9452-4ffd-b6b8-9f906e523c70",
      "loc": "530 -160",
      "size": "",
      "description": "",
      "markedAsDeleted": false,
      "modified": true
    },
    {
      "id": "90f2ea11-d248-4050-c608-852293592021",
      "name": "",
      "typeRef": "7e9386c9-75bc-4239-c040-d328f1c91e1b",
      "metamodelRef": "f3e2467f-9452-4ffd-b6b8-9f906e523c70",
      "loc": "250 -220",
      "size": "",
      "description": "",
      "markedAsDeleted": false,
      "modified": true
    },
    {
      "id": "a7249b06-238c-4e38-d48f-88aa04039976",
      "name": "",
      "typeRef": "4beef970-06ed-4f54-6589-5804e358a8a6",
      "metamodelRef": "f3e2467f-9452-4ffd-b6b8-9f906e523c70",
      "loc": "-150 50",
      "size": "",
      "description": "",
      "markedAsDeleted": false,
      "modified": true
    },
    {
      "id": "c4521f23-3a2d-4c80-c531-aae7a48ba7b1",
      "name": "",
      "typeRef": "91c27596-9910-49c3-9088-44da75085f14",
      "metamodelRef": "f3e2467f-9452-4ffd-b6b8-9f906e523c70",
      "loc": "-440 40",
      "size": "",
      "description": "",
      "markedAsDeleted": false,
      "modified": true
    },
    {
      "id": "6ce6b952-79f0-4b93-59e9-2305f5354092",
      "name": "",
      "typeRef": "1b6ba1b5-f716-4777-deab-cf91b0f53218",
      "metamodelRef": "f3e2467f-9452-4ffd-b6b8-9f906e523c70",
      "loc": "-380 -330",
      "size": "",
      "description": "",
      "markedAsDeleted": false,
      "modified": true
    },
    {
      "id": "0cbab118-e55b-48c6-faca-0fbf7821d649",
      "name": "",
      "typeRef": "7b543680-f667-4db7-2344-8af95e654941",
      "metamodelRef": "f3e2467f-9452-4ffd-b6b8-9f906e523c70",
      "loc": "490 190",
      "size": "100 50",
      "description": "",
      "markedAsDeleted": false,
      "modified": true
    },
    {
      "id": "5975ebb1-69fc-421b-b67a-86be56650231",
      "name": "",
      "typeRef": "5f1fa0f1-d89f-4a62-5b93-3a433acb833e",
      "metamodelRef": "f3e2467f-9452-4ffd-b6b8-9f906e523c70",
      "loc": "",
      "size": "",
      "description": "",
      "markedAsDeleted": false,
      "modified": false
    },
    {
      "id": "9958887a-1a8b-451d-4c1d-a3c530eb6879",
      "name": "",
      "typeRef": "c30f6e2c-d04b-4360-fc17-002d1c4162f8",
      "metamodelRef": "f3e2467f-9452-4ffd-b6b8-9f906e523c70",
      "loc": "",
      "size": "",
      "description": "",
      "markedAsDeleted": false,
      "modified": false
    },
    {
      "id": "67866694-39b2-423f-4cda-3dd56a99cf53",
      "name": "",
      "typeRef": "c0de4b48-0220-424a-dd07-e620e27bd3c8",
      "metamodelRef": "f3e2467f-9452-4ffd-b6b8-9f906e523c70",
      "loc": "",
      "size": "",
      "description": "",
      "markedAsDeleted": false,
      "modified": false
    },
    {
      "id": "1972273a-860b-4cff-5dca-b3192a8a1f81",
      "name": "",
      "typeRef": "31a18ce8-66cf-4b95-79e4-673746867ac3",
      "metamodelRef": "f3e2467f-9452-4ffd-b6b8-9f906e523c70",
      "loc": "",
      "size": "",
      "description": "",
      "markedAsDeleted": false,
      "modified": false
    },
    {
      "id": "e3203e4b-4716-4985-7fb2-1afb9e3ba87c",
      "name": "",
      "typeRef": "e07dbd76-f1ec-492e-cfce-c8cb5a2fab3c",
      "metamodelRef": "f3e2467f-9452-4ffd-b6b8-9f906e523c70",
      "loc": "",
      "size": "",
      "description": "",
      "markedAsDeleted": false,
      "modified": false
    },
    {
      "id": "35246249-02fd-4224-49ae-e34aad06a6a5",
      "name": "",
      "typeRef": "5cc540c0-ea91-4401-74bb-4f7cb52a2366",
      "metamodelRef": "f3e2467f-9452-4ffd-b6b8-9f906e523c70",
      "loc": "",
      "size": "",
      "description": "",
      "markedAsDeleted": false,
      "modified": false
    },
    {
      "id": "28f5a686-0c35-43fd-749b-ef2e7e081cd0",
      "name": "",
      "typeRef": "b5cd30a2-6213-402a-a64a-85c6eff312f5",
      "metamodelRef": "f3e2467f-9452-4ffd-b6b8-9f906e523c70",
      "loc": "",
      "size": "",
      "description": "",
      "markedAsDeleted": false,
      "modified": false
    },
    {
      "id": "696a1da9-a661-48d7-ec39-46d525db7b51",
      "name": "",
      "typeRef": "c7b60c43-cb91-4e92-a4b6-53d2aba052f3",
      "metamodelRef": "f3e2467f-9452-4ffd-b6b8-9f906e523c70",
      "loc": "",
      "size": "",
      "description": "",
      "markedAsDeleted": false,
      "modified": false
    },
    {
      "id": "683a152a-e164-4115-2e83-aefb91b1c135",
      "name": "",
      "typeRef": "4f1e3080-24b0-4e9f-f8cc-f13e469232a2",
      "metamodelRef": "f3e2467f-9452-4ffd-b6b8-9f906e523c70",
      "loc": "",
      "size": "",
      "description": "",
      "markedAsDeleted": false,
      "modified": false
    },
    {
      "id": "f91f572c-9718-4447-94ea-e8ad762a6585",
      "name": "",
      "typeRef": "e0708fcb-4dab-44fb-312d-7685ea332985",
      "metamodelRef": "f3e2467f-9452-4ffd-b6b8-9f906e523c70",
      "loc": "",
      "size": "",
      "description": "",
      "markedAsDeleted": false,
      "modified": false
    },
    {
      "id": "4da3e691-e485-49f4-7940-475a20161e93",
      "name": "",
      "typeRef": "7e9386c9-75bc-4239-c040-d328f1c91e1b",
      "metamodelRef": "f3e2467f-9452-4ffd-b6b8-9f906e523c70",
      "loc": "",
      "size": "",
      "description": "",
      "markedAsDeleted": false,
      "modified": false
    },
    {
      "id": "83e6eecf-22a6-4000-24e0-83a819fa9b87",
      "name": "",
      "typeRef": "4beef970-06ed-4f54-6589-5804e358a8a6",
      "metamodelRef": "f3e2467f-9452-4ffd-b6b8-9f906e523c70",
      "loc": "",
      "size": "",
      "description": "",
      "markedAsDeleted": false,
      "modified": false
    },
    {
      "id": "baa02f33-54dd-4fac-cf52-14ee326f0fa0",
      "name": "",
      "typeRef": "91c27596-9910-49c3-9088-44da75085f14",
      "metamodelRef": "f3e2467f-9452-4ffd-b6b8-9f906e523c70",
      "loc": "",
      "size": "",
      "description": "",
      "markedAsDeleted": false,
      "modified": false
    },
    {
      "id": "970c637c-4652-4288-55d7-d6b33b093c0e",
      "name": "",
      "typeRef": "1b6ba1b5-f716-4777-deab-cf91b0f53218",
      "metamodelRef": "f3e2467f-9452-4ffd-b6b8-9f906e523c70",
      "loc": "",
      "size": "",
      "description": "",
      "markedAsDeleted": false,
      "modified": false
    }
  ],
  "relshiptypeviews": [
    {
      "id": "c52b2c07-671e-45dc-6488-672acaa9ac3c",
      "name": "Is_Generalization",
      "description": "",
      "typeRef": "ebae050f-31cc-4b9a-c492-1ed65289a520",
      "template": "linkTemplate1",
      "strokecolor": "black",
      "strokewidth": "1",
      "textcolor": "black",
      "textscale": "1",
      "dash": "None",
      "fromArrow": "None",
      "toArrow": "Triangle",
      "fromArrowColor": " ",
      "toArrowColor": "white",
      "routing": "",
      "corner": "",
      "curve": "",
      "markedAsDeleted": false,
      "modified": false
    },
    {
      "id": "2188d263-8a0f-4d76-3d09-d6cfe555e027",
      "name": "has_Association",
      "description": "",
      "typeRef": "94b66a28-b600-4430-311a-83444e55a05c",
      "template": "linkTemplate1",
      "strokecolor": "black",
      "strokewidth": "1",
      "textcolor": "black",
      "textscale": "1",
      "dash": "None",
      "fromArrow": "None",
      "toArrow": "OpenTriangle",
      "fromArrowColor": "",
      "toArrowColor": "white",
      "routing": "",
      "corner": "",
      "curve": "",
      "markedAsDeleted": false,
      "modified": false
    }
  ],
  "generatedFromModelRef": "05d5b929-b985-49ac-cf92-cc095a03889z",
  "includeInheritedReltypes": true,
  "includeSystemtypes": true,
  "layout": "ForceDirected",
  "routing": "Normal",
  "linkcurve": "None",
  "markedAsDeleted": false,
  "modified": false
}